duppla_slack/__init__.py
duppla_slack/py.typed
duppla_slack/constants/__init__.py
duppla_slack/constants/channels.py
duppla_slack/constants/py.typed
duppla_slack/constants/templates.py
duppla_slack/models/__init__.py
duppla_slack/models/duppla.py
duppla_slack/models/message.py
duppla_slack/models/py.typed
duppla_slack/models/response.py
duppla_slack/models/slack_types.py
duppla_slack/service/__init__.py
duppla_slack/service/block_builder.py
duppla_slack/service/listeners.py
duppla_slack/service/public.py
duppla_slack/service/py.typed
duppla_slack/utils/__init__.py
duppla_slack/utils/rate_limiter.py
duppla_slack-2025.11.15.14.53.dist-info/LICENSE
duppla_slack-2025.11.15.14.53.dist-info/METADATA
duppla_slack-2025.11.15.14.53.dist-info/WHEEL
duppla_slack-2025.11.15.14.53.dist-info/top_level.txt
duppla_slack-2025.11.15.14.53.dist-info/RECORD
